bendeep/__init__.py
bendeep/sentiment.py
bendeep/translation.py
bendeep/utils.py
bendeep-1.2.dist-info/LICENSE
bendeep-1.2.dist-info/METADATA
bendeep-1.2.dist-info/WHEEL
bendeep-1.2.dist-info/top_level.txt
bendeep-1.2.dist-info/RECORD
