Metadata-Version: 2.1
Name: bendeep
Version: 1.2
Summary: BENDeep is a pytorch based deep learning solution for Bengali NLP Task
Home-page: https://github.com/sagorbrur/bendeep
Author: Sagor Sarker
Author-email: sagorhem3532@gmail.com
License: MIT
Platform: UNKNOWN
Classifier: Programming Language :: Python :: 3
Classifier: License :: OSI Approved :: MIT License
Classifier: Operating System :: OS Independent
Requires-Python: >=3.5
Requires-Dist: pandas
Requires-Dist: tqdm
Requires-Dist: scikit-learn
Requires-Dist: matplotlib
Requires-Dist: numpy
